ppc/__init__.py
ppc/__main__.py
ppc/python_project_creator.py
ppc/templates/basic/main.py
ppc/templates/cp/input.txt
ppc/templates/cp/main.py
ppc/templates/cp/output.txt
ppc/templates/pip/README.md
ppc/templates/pip/__ppc__.toml
ppc/templates/pip/main.py
ppc/templates/pip/setup.py
ppc/templates/pip/__package_name__/__init__.py
python_project_creator-0.1.0.dist-info/LICENSE
python_project_creator-0.1.0.dist-info/METADATA
python_project_creator-0.1.0.dist-info/WHEEL
python_project_creator-0.1.0.dist-info/entry_points.txt
python_project_creator-0.1.0.dist-info/top_level.txt
python_project_creator-0.1.0.dist-info/RECORD
