Metadata-Version: 2.1
Name: python-project-creator
Version: 0.1.0
Summary: It is a code generator for Python projects.
Home-page: https://github.com/ThiNepo/python-project-creator
Author: Thiago Nepomuceno
Author-email: thi.nepo@gmail.com
License: UNKNOWN
Platform: UNKNOWN
Classifier: Programming Language :: Python :: 3
Classifier: License :: OSI Approved :: GNU General Public License v3 or later (GPLv3+)
Classifier: Operating System :: OS Independent
License-File: LICENSE
Requires-Dist: toml
Requires-Dist: click
